theloop/__init__.py
theloop/cli.py
theloop/interfaces.py
theloop/services/__init__.py
theloop/services/config_manager.py
theloop/services/gcp_uploader.py
theloop/services/logging_configurator.py
theloop-0.1.0.dist-info/METADATA
theloop-0.1.0.dist-info/WHEEL
theloop-0.1.0.dist-info/entry_points.txt
theloop-0.1.0.dist-info/RECORD
