Metadata-Version: 2.4
Name: theloop
Version: 0.1.0
Summary: Upload files from URLs to cloud storage
Project-URL: Homepage, https://github.com/matterai/theloop
Project-URL: Repository, https://github.com/matterai/theloop
Project-URL: Issues, https://github.com/matterai/theloop/issues
Author-email: Vladimir Vlasiuk <matterai.net@gmail.com>
Keywords: cli,cloud,gcp,storage,upload
Classifier: License :: OSI Approved :: MIT License
Classifier: Programming Language :: Python :: 3
Classifier: Programming Language :: Python :: 3.11
Requires-Python: >=3.11
Requires-Dist: aiohttp==3.11.18
Requires-Dist: click<8.2,>=8.1
Requires-Dist: google-cloud-storage==3.1.0
Requires-Dist: pydantic==2.11.4
Requires-Dist: requests==2.32.3
Requires-Dist: tqdm==4.67.1
Requires-Dist: typer==0.15.4
